examplepkg_mj/__init__.py
examplepkg_mj-0.0.1.dist-info/LICENSE
examplepkg_mj-0.0.1.dist-info/METADATA
examplepkg_mj-0.0.1.dist-info/WHEEL
examplepkg_mj-0.0.1.dist-info/top_level.txt
examplepkg_mj-0.0.1.dist-info/RECORD
