Metadata-Version: 2.1
Name: examplepkg-mj
Version: 0.0.1
Summary: An example package
Home-page: https://github.com/soundpainter/sampleproject
Author: Minjong Kim
Author-email: minjong.kim@gmail.com
License: UNKNOWN
Platform: UNKNOWN
Classifier: Programming Language :: Python :: 3
Classifier: License :: OSI Approved :: MIT License
Classifier: Operating System :: OS Independent
